reflame/__init__.py
reflame/base_flnn.py
reflame/base_flnn_torch.py
reflame/model/__init__.py
reflame/model/mha_flnn.py
reflame/model/standard_flnn.py
reflame/utils/__init__.py
reflame/utils/activation.py
reflame/utils/data_toolkit.py
reflame/utils/evaluator.py
reflame/utils/expand_util.py
reflame/utils/validator.py
reflame-1.0.1.dist-info/LICENSE
reflame-1.0.1.dist-info/METADATA
reflame-1.0.1.dist-info/WHEEL
reflame-1.0.1.dist-info/top_level.txt
reflame-1.0.1.dist-info/RECORD
